dgl_cu90-0.5.3.data/purelib/dgl/__init__.py
dgl_cu90-0.5.3.data/purelib/dgl/_api_internal.py
dgl_cu90-0.5.3.data/purelib/dgl/base.py
dgl_cu90-0.5.3.data/purelib/dgl/batch.py
dgl_cu90-0.5.3.data/purelib/dgl/container.py
dgl_cu90-0.5.3.data/purelib/dgl/convert.py
dgl_cu90-0.5.3.data/purelib/dgl/core.py
dgl_cu90-0.5.3.data/purelib/dgl/dgl.dll
dgl_cu90-0.5.3.data/purelib/dgl/frame.py
dgl_cu90-0.5.3.data/purelib/dgl/generators.py
dgl_cu90-0.5.3.data/purelib/dgl/graph_index.py
dgl_cu90-0.5.3.data/purelib/dgl/heterograph.py
dgl_cu90-0.5.3.data/purelib/dgl/heterograph_index.py
dgl_cu90-0.5.3.data/purelib/dgl/init.py
dgl_cu90-0.5.3.data/purelib/dgl/ndarray.py
dgl_cu90-0.5.3.data/purelib/dgl/network.py
dgl_cu90-0.5.3.data/purelib/dgl/partition.py
dgl_cu90-0.5.3.data/purelib/dgl/propagate.py
dgl_cu90-0.5.3.data/purelib/dgl/random.py
dgl_cu90-0.5.3.data/purelib/dgl/readout.py
dgl_cu90-0.5.3.data/purelib/dgl/sparse.py
dgl_cu90-0.5.3.data/purelib/dgl/subgraph.py
dgl_cu90-0.5.3.data/purelib/dgl/transform.py
dgl_cu90-0.5.3.data/purelib/dgl/traversal.py
dgl_cu90-0.5.3.data/purelib/dgl/udf.py
dgl_cu90-0.5.3.data/purelib/dgl/view.py
dgl_cu90-0.5.3.data/purelib/dgl/_deprecate/__init__.py
dgl_cu90-0.5.3.data/purelib/dgl/_deprecate/frame.py
dgl_cu90-0.5.3.data/purelib/dgl/_deprecate/graph.py
dgl_cu90-0.5.3.data/purelib/dgl/_deprecate/kernel.py
dgl_cu90-0.5.3.data/purelib/dgl/_deprecate/nodeflow.py
dgl_cu90-0.5.3.data/purelib/dgl/_deprecate/udf.py
dgl_cu90-0.5.3.data/purelib/dgl/_deprecate/view.py
dgl_cu90-0.5.3.data/purelib/dgl/_deprecate/runtime/__init__.py
dgl_cu90-0.5.3.data/purelib/dgl/_deprecate/runtime/adapter.py
dgl_cu90-0.5.3.data/purelib/dgl/_deprecate/runtime/degree_bucketing.py
dgl_cu90-0.5.3.data/purelib/dgl/_deprecate/runtime/runtime.py
dgl_cu90-0.5.3.data/purelib/dgl/_deprecate/runtime/scheduler.py
dgl_cu90-0.5.3.data/purelib/dgl/_deprecate/runtime/spmv.py
dgl_cu90-0.5.3.data/purelib/dgl/_deprecate/runtime/ir/__init__.py
dgl_cu90-0.5.3.dist-info/METADATA
dgl_cu90-0.5.3.dist-info/WHEEL
dgl_cu90-0.5.3.dist-info/top_level.txt
dgl_cu90-0.5.3.dist-info/RECORD
